dumb_udev/__init__.py
dumb_udev/__main__.py
dumb_udev/metadata.py
dumb_udev/service.py
dumb_udev/version
dumb_udev-1.0.2.dist-info/LICENSE
dumb_udev-1.0.2.dist-info/METADATA
dumb_udev-1.0.2.dist-info/WHEEL
dumb_udev-1.0.2.dist-info/entry_points.txt
dumb_udev-1.0.2.dist-info/top_level.txt
dumb_udev-1.0.2.dist-info/RECORD
