Metadata-Version: 2.1
Name: dumb-udev
Version: 1.0.2
Summary: A simple tool designed to bridge input devices, such as keyboards and mice, to output devices.
Home-page: https://github.com/Josh5/dumb_udev
Author: Josh.5
Author-email: jsunnex@gmail.com
Maintainer: Josh.5
Maintainer-email: jsunnex@gmail.com
License: GPLv3
Classifier: Development Status :: 5 - Production/Stable
Classifier: Intended Audience :: End Users/Desktop
Classifier: Intended Audience :: Developers
Classifier: Programming Language :: Python :: 3.7
Classifier: Programming Language :: Python :: 3.8
Classifier: Programming Language :: Python :: 3.9
Classifier: Programming Language :: Python :: 3.10
Classifier: Programming Language :: Python :: 3.11
Classifier: Operating System :: POSIX :: Linux
Classifier: Operating System :: Unix
Classifier: License :: OSI Approved :: GNU General Public License v3 (GPLv3)
Classifier: Topic :: Multimedia :: Video :: Conversion
Classifier: Topic :: Internet :: WWW/HTTP
Requires-Python: >=3.7
License-File: LICENSE
Requires-Dist: murmurhash2 (==0.2.10)
Requires-Dist: pyudev (==0.24.1)
